joes_giant_toolbox/__init__.py
joes_giant_toolbox/convenience.py
joes_giant_toolbox/custom_exceptions.py
joes_giant_toolbox/dataviz.py
joes_giant_toolbox/google_cloud.py
joes_giant_toolbox/maths.py
joes_giant_toolbox/proj_mgmt.py
joes_giant_toolbox/sklearn.py
joes_giant_toolbox/stats.py
joes_giant_toolbox/text.py
joes_giant_toolbox/web.py
joes_giant_toolbox/all/__init__.py
joes_giant_toolbox/all/anonymous_view_public_linkedin_page.py
joes_giant_toolbox/all/ascii_density_histogram.py
joes_giant_toolbox/all/compare_metric_to_prev_period.py
joes_giant_toolbox/all/conjugate_prior_beta_binomial.py
joes_giant_toolbox/all/cosine_similarity.py
joes_giant_toolbox/all/create_gcloud_vm_docker_template.py
joes_giant_toolbox/all/create_parallel_google_cloud_run_job_template.py
joes_giant_toolbox/all/create_project_scope_doc.py
joes_giant_toolbox/all/data_batcher.py
joes_giant_toolbox/all/delete_file_in_gcloud_bucket.py
joes_giant_toolbox/all/download_file_from_gcloud_bucket_to_python.py
joes_giant_toolbox/all/duckduckgo_search_multipage.py
joes_giant_toolbox/all/gcloud_vm_deletes_itself.py
joes_giant_toolbox/all/list_all_python_imports.py
joes_giant_toolbox/all/list_files_in_gcloud_bucket.py
joes_giant_toolbox/all/longest_common_substring.py
joes_giant_toolbox/all/longest_sentence_subsequence_plagiarism_detector.py
joes_giant_toolbox/all/make_url_request.py
joes_giant_toolbox/all/manual_keyword_classifier.py
joes_giant_toolbox/all/move_or_rename_file_in_gcloud_bucket.py
joes_giant_toolbox/all/parse_mime_email_parts.py
joes_giant_toolbox/all/print_progress_bar.py
joes_giant_toolbox/all/python_plotting_tutorials.py
joes_giant_toolbox/all/query_bigquery_to_pandas_df.py
joes_giant_toolbox/all/rapid_binary_classifier.py
joes_giant_toolbox/all/regex_rules_classifier.py
joes_giant_toolbox/all/require_api_key.py
joes_giant_toolbox/all/retry_function_call.py
joes_giant_toolbox/all/run_python_function_in_parallel.py
joes_giant_toolbox/all/scrape_webpage_and_all_linked_webpages.py
joes_giant_toolbox-0.9.0.dist-info/LICENSE
joes_giant_toolbox-0.9.0.dist-info/METADATA
joes_giant_toolbox-0.9.0.dist-info/WHEEL
joes_giant_toolbox-0.9.0.dist-info/top_level.txt
joes_giant_toolbox-0.9.0.dist-info/RECORD
