Metadata-Version: 2.1
Name: joes_giant_toolbox
Version: 0.9.0
Summary: A large collection of general python functions and classes that I use in my daily work
Author-email: Joseph Bolton <joseph.jazz.bolton@gmail.com>
License: GNU GENERAL PUBLIC LICENSE
Project-URL: Homepage, https://github.com/J-sephB-lt-n/joes_giant_toolbox
Keywords: api,web,dataviz,google cloud,project management,convenience,statistics,hypothesis testing,machine learning,NLP
Classifier: License :: OSI Approved :: GNU General Public License v3 (GPLv3)
Classifier: Programming Language :: Python
Classifier: Programming Language :: Python :: 3
Requires-Python: >=3.9
License-File: LICENSE
Provides-Extra: dev
Requires-Dist: black ; extra == 'dev'
Requires-Dist: pytest ; extra == 'dev'
Provides-Extra: doc
Requires-Dist: m2r ; extra == 'doc'
Requires-Dist: sphinx ; extra == 'doc'
Provides-Extra: google
Requires-Dist: db-dtypes ==1.0.5 ; extra == 'google'
Requires-Dist: google-cloud-bigquery ==3.4.1 ; extra == 'google'
Requires-Dist: google-cloud-bigquery-storage ==2.18 ; extra == 'google'
Requires-Dist: google-cloud-compute ==1.10.0 ; extra == 'google'
Requires-Dist: google-cloud-logging ==3.5.0 ; extra == 'google'
Requires-Dist: google-cloud-storage ==2.7.0 ; extra == 'google'
